my_package/__init__.py
my_package/code_generator.py
verify_project_demo-0.1.0.dist-info/LICENSE
verify_project_demo-0.1.0.dist-info/METADATA
verify_project_demo-0.1.0.dist-info/WHEEL
verify_project_demo-0.1.0.dist-info/top_level.txt
verify_project_demo-0.1.0.dist-info/RECORD
