Metadata-Version: 2.1
Name: verify-project-demo
Version: 0.1.0
Summary: A sample Python package that generates test code.
Home-page: https://github.com/yourusername/verify-project-demo
Author: Your Name
Author-email: your.email@example.com
Classifier: Programming Language :: Python :: 3
Classifier: License :: OSI Approved :: MIT License
Classifier: Operating System :: OS Independent
Requires-Python: >=3.6
License-File: LICENSE
